[
    {
        "Humans and monsters share the same world": {
            "phrases": [
                "Humans and monsters share the same world"
            ],
            "words": [
                "Humans",
                "and",
                "monsters",
                "share",
                "the",
                "same",
                "world"
            ]
        }
    },
    {
        "They exist on opposite side of the Ying Yang": {
            "phrases": [
                "They exist on opposite side of the Ying Yang"
            ],
            "words": [
                "They",
                "exist",
                "on",
                "opposite",
                "side",
                "of",
                "the",
                "Ying",
                "Yang"
            ]
        }
    },
    {
        "So they coexist peacefully": {
            "phrases": [
                "So they coexist peacefully"
            ],
            "words": [
                "So",
                "they",
                "coexist",
                "peacefully"
            ]
        }
    },
    {
        "But recently,": {
            "phrases": [
                "But recently,"
            ],
            "words": [
                "But",
                "recently",
                ","
            ]
        }
    },
    {
        "The system is in disarray": {
            "phrases": [
                "The system is in disarray"
            ],
            "words": [
                "The",
                "system",
                "is",
                "in",
                "disarray"
            ]
        }
    },
    {
        "The Yin Yang has broken": {
            "phrases": [
                "The Yin Yang has broken"
            ],
            "words": [
                "The",
                "Yin",
                "Yang",
                "has",
                "broken"
            ]
        }
    },
    {
        "And abnormalities occur": {
            "phrases": [
                "And abnormalities occur"
            ],
            "words": [
                "And",
                "abnormalities",
                "occur"
            ]
        }
    },
    {
        "The world is in chaos": {
            "phrases": [
                "The world is in chaos"
            ],
            "words": [
                "The",
                "world",
                "is",
                "in",
                "chaos"
            ]
        }
    },
    {
        "I must find the key to saving this earth": {
            "phrases": [
                "I must find the key to saving this earth"
            ],
            "words": [
                "I",
                "must",
                "find",
                "the",
                "key",
                "to",
                "saving",
                "this",
                "earth"
            ]
        }
    },
    {
        "Or,": {
            "phrases": [
                "Or,"
            ],
            "words": [
                "Or",
                ","
            ]
        }
    },
    {
        "I'll become the key itself": {
            "phrases": [
                "I will become the key itself"
            ],
            "words": [
                "I",
                "will",
                "become",
                "the",
                "key",
                "itself"
            ]
        }
    },
    {
        "Student, don't make rash decisions": {
            "phrases": [
                "Student, do not make rash decisions"
            ],
            "words": [
                "Student",
                ",",
                "do",
                "not",
                "make",
                "rash",
                "decisions"
            ]
        }
    },
    {
        "90 of people are troubled in some way": {
            "phrases": [
                "90 of people are troubled in some way"
            ],
            "words": [
                "90",
                "of",
                "people",
                "are",
                "troubled",
                "in",
                "some",
                "way"
            ]
        }
    },
    {
        "Living will result in facing those problems": {
            "phrases": [
                "Living will result in facing those problems"
            ],
            "words": [
                "Living",
                "will",
                "result",
                "in",
                "facing",
                "those",
                "problems"
            ]
        }
    },
    {
        "Sports betting is harmful": {
            "phrases": [
                "Sports betting is harmful"
            ],
            "words": [
                "Sports",
                "betting",
                "is",
                "harmful"
            ]
        }
    },
    {
        "Avoid the World Cup": {
            "phrases": [
                "Avoid the World Cup"
            ],
            "words": [
                "Avoid",
                "the",
                "World",
                "Cup"
            ]
        }
    },
    {
        "Any problem came be overcome": {
            "phrases": [
                "Any problem came be overcome"
            ],
            "words": [
                "Any",
                "problem",
                "came",
                "be",
                "overcome"
            ]
        }
    },
    {
        "The struggles in life will only improve your brilliance": {
            "phrases": [
                "The struggles in life will only improve your brilliance"
            ],
            "words": [
                "The",
                "struggles",
                "in",
                "life",
                "will",
                "only",
                "improve",
                "your",
                "brilliance"
            ]
        }
    },
    {
        "Student, do not make rash decisions": {
            "phrases": [
                "Student, do not make rash decisions"
            ],
            "words": [
                "Student",
                ",",
                "do",
                "not",
                "make",
                "rash",
                "decisions"
            ]
        }
    },
    {
        "What is with this tone of pity?": {
            "phrases": [
                "What is with this tone of pity?"
            ],
            "words": [
                "What",
                "is",
                "with",
                "this",
                "tone",
                "of",
                "pity",
                "?"
            ]
        }
    },
    {
        "I never said I was jumping!": {
            "phrases": [
                "I never said I was jumping!"
            ],
            "words": [
                "I",
                "never",
                "said",
                "I",
                "was",
                "jumping",
                "!"
            ]
        }
    },
    {
        "Also,": {
            "phrases": [
                "Also,"
            ],
            "words": [
                "Also",
                ","
            ]
        }
    },
    {
        "Is this the only thing you know how to say?": {
            "phrases": [
                "Is this the only thing you know how to say?"
            ],
            "words": [
                "Is",
                "this",
                "the",
                "only",
                "thing",
                "you",
                "know",
                "how",
                "to",
                "say",
                "?"
            ]
        }
    },
    {
        "Enough is enough!": {
            "phrases": [
                "Enough is enough!"
            ],
            "words": [
                "Enough",
                "is",
                "enough",
                "!"
            ]
        }
    },
    {
        "I'm not going to jump!": {
            "phrases": [
                "I am not going to jump!"
            ],
            "words": [
                "I",
                "am",
                "not",
                "going",
                "to",
                "jump",
                "!"
            ]
        }
    },
    {
        "How many times to I have to say it!": {
            "phrases": [
                "How many times to I have to say it!"
            ],
            "words": [
                "How",
                "many",
                "times",
                "to",
                "I",
                "have",
                "to",
                "say",
                "it",
                "!"
            ]
        }
    },
    {
        "AHH!!!": {
            "phrases": [
                "AHH!!!"
            ],
            "words": [
                "AHH",
                "!!!"
            ]
        }
    },
    {
        "You,": {
            "phrases": [
                "You,"
            ],
            "words": [
                "You",
                ","
            ]
        }
    },
    {
        "Who are you?": {
            "phrases": [
                "Who are you?"
            ],
            "words": [
                "Who",
                "are",
                "you",
                "?"
            ]
        }
    },
    {
        "What's your business here?": {
            "phrases": [
                "What is your business here?"
            ],
            "words": [
                "What",
                "is",
                "your",
                "business",
                "here",
                "?"
            ]
        }
    },
    {
        "Huh?": {
            "phrases": [
                "Huh?"
            ],
            "words": [
                "Huh",
                "?"
            ]
        }
    },
    {
        "That should be my question": {
            "phrases": [
                "That should be my question"
            ],
            "words": [
                "That",
                "should",
                "be",
                "my",
                "question"
            ]
        }
    },
    {
        "Alone by yourself on the 20th floor": {
            "phrases": [
                "Alone by yourself on the 20th floor"
            ],
            "words": [
                "Alone",
                "by",
                "yourself",
                "on",
                "the",
                "20th",
                "floor"
            ]
        }
    },
    {
        "And also wearing such strange clothes": {
            "phrases": [
                "And also wearing such strange clothes"
            ],
            "words": [
                "And",
                "also",
                "wearing",
                "such",
                "strange",
                "clothes"
            ]
        }
    },
    {
        "Take a look at yourself!": {
            "phrases": [
                "Take a look at yourself!"
            ],
            "words": [
                "Take",
                "a",
                "look",
                "at",
                "yourself",
                "!"
            ]
        }
    },
    {
        "I'm just expressing myself": {
            "phrases": [
                "I am just expressing myself"
            ],
            "words": [
                "I",
                "am",
                "just",
                "expressing",
                "myself"
            ]
        }
    },
    {
        "It's called the lonely mushroom": {
            "phrases": [
                "It is called the lonely mushroom"
            ],
            "words": [
                "It",
                "is",
                "called",
                "the",
                "lonely",
                "mushroom"
            ]
        }
    },
    {
        "If it wasn't for your humanity": {
            "phrases": [
                "If it was not for your humanity"
            ],
            "words": [
                "If",
                "it",
                "was",
                "not",
                "for",
                "your",
                "humanity"
            ]
        }
    },
    {
        "Then I would've cut you down already!": {
            "phrases": [
                "Then I would have cut you down already!"
            ],
            "words": [
                "Then",
                "I",
                "would",
                "have",
                "cut",
                "you",
                "down",
                "already",
                "!"
            ]
        }
    },
    {
        "Stop it! You guys!": {
            "phrases": [
                "Stop it!",
                "You guys!"
            ],
            "words": [
                "Stop",
                "it",
                "!",
                "You",
                "guys",
                "!"
            ]
        }
    },
    {
        "Stop repeating!": {
            "phrases": [
                "Stop repeating!"
            ],
            "words": [
                "Stop",
                "repeating",
                "!"
            ]
        }
    },
    {
        "So many police have been dispatched": {
            "phrases": [
                "So many police have been dispatched"
            ],
            "words": [
                "So",
                "many",
                "police",
                "have",
                "been",
                "dispatched"
            ]
        }
    },
    {
        "Is it really necessary?": {
            "phrases": [
                "Is it really necessary?"
            ],
            "words": [
                "Is",
                "it",
                "really",
                "necessary",
                "?"
            ]
        }
    },
    {
        "I'm not going to jump!": {
            "phrases": [
                "I am not going to jump!"
            ],
            "words": [
                "I",
                "am",
                "not",
                "going",
                "to",
                "jump",
                "!"
            ]
        }
    },
    {
        "Do what your supposed to do!": {
            "phrases": [
                "Do what your supposed to do!"
            ],
            "words": [
                "Do",
                "what",
                "your",
                "supposed",
                "to",
                "do",
                "!"
            ]
        }
    },
    {
        "Can you not hear me?": {
            "phrases": [
                "Can you not hear me?"
            ],
            "words": [
                "Can",
                "you",
                "not",
                "hear",
                "me",
                "?"
            ]
        }
    },
    {
        "I'm seriously not going to jump!": {
            "phrases": [
                "I am seriously not going to jump!"
            ],
            "words": [
                "I",
                "am",
                "seriously",
                "not",
                "going",
                "to",
                "jump",
                "!"
            ]
        }
    },
    {
        "Please believe in me!": {
            "phrases": [
                "Please believe in me!"
            ],
            "words": [
                "Please",
                "believe",
                "in",
                "me",
                "!"
            ]
        }
    },
    {
        "You can leave now": {
            "phrases": [
                "You can leave now"
            ],
            "words": [
                "You",
                "can",
                "leave",
                "now"
            ]
        }
    },
    {
        "Hurry up and leave!": {
            "phrases": [
                "Hurry up and leave!"
            ],
            "words": [
                "Hurry",
                "up",
                "and",
                "leave",
                "!"
            ]
        }
    },
    {
        "Please, please, please": {
            "phrases": [
                "Please, please, please"
            ],
            "words": [
                "Please",
                ",",
                "please",
                ",",
                "please"
            ]
        }
    },
    {
        "Angle is OK": {
            "phrases": [
                "Angle is OK"
            ],
            "words": [
                "Angle",
                "is",
                "OK"
            ]
        }
    },
    {
        "Direction is OK": {
            "phrases": [
                "Direction is OK"
            ],
            "words": [
                "Direction",
                "is",
                "OK"
            ]
        }
    },
    {
        "Gravity is OK": {
            "phrases": [
                "Gravity is OK"
            ],
            "words": [
                "Gravity",
                "is",
                "OK"
            ]
        }
    },
    {
        "Young girl,": {
            "phrases": [
                "Young girl,"
            ],
            "words": [
                "Young",
                "girl",
                ","
            ]
        }
    },
    {
        "I'm here to save you": {
            "phrases": [
                "I am here to save you"
            ],
            "words": [
                "I",
                "am",
                "here",
                "to",
                "save",
                "you"
            ]
        }
    },
    {
        "Here I come!": {
            "phrases": [
                "Here I come!"
            ],
            "words": [
                "Here",
                "I",
                "come",
                "!"
            ]
        }
    },
    {
        "How did it really turn into a suicide?": {
            "phrases": [
                "How did it really turn into a suicide?"
            ],
            "words": [
                "How",
                "did",
                "it",
                "really",
                "turn",
                "into",
                "a",
                "suicide",
                "?"
            ]
        }
    },
    {
        "I didn't do it on purpose!": {
            "phrases": [
                "I did not do it on purpose!"
            ],
            "words": [
                "I",
                "did",
                "not",
                "do",
                "it",
                "on",
                "purpose",
                "!"
            ]
        }
    },
    {
        "Phew,": {
            "phrases": [
                "Phew,"
            ],
            "words": [
                "Phew",
                ","
            ]
        }
    },
    {
        "At least she didn't die": {
            "phrases": [
                "At least she did not die"
            ],
            "words": [
                "At",
                "least",
                "she",
                "did",
                "not",
                "die"
            ]
        }
    },
    {
        "Class is finally over": {
            "phrases": [
                "Class is finally over"
            ],
            "words": [
                "Class",
                "is",
                "finally",
                "over"
            ]
        }
    },
    {
        "If it doesn't end, then I'll just leave": {
            "phrases": [
                "If it does not end, then I will just leave"
            ],
            "words": [
                "If",
                "it",
                "does",
                "not",
                "end",
                ",",
                "then",
                "I",
                "will",
                "just",
                "leave"
            ]
        }
    },
    {
        "My cravings have already kicked in": {
            "phrases": [
                "My cravings have already kicked in"
            ],
            "words": [
                "My",
                "cravings",
                "have",
                "already",
                "kicked",
                "in"
            ]
        }
    },
    {
        "Big bro, take it easy": {
            "phrases": [
                "Big bro, take it easy"
            ],
            "words": [
                "Big",
                "bro",
                ",",
                "take",
                "it",
                "easy"
            ]
        }
    },
    {
        "If our teacher saw you smoking in class he'll probably have a heart attack": {
            "phrases": [
                "If our teacher saw you smoking in class he will probably have a heart attack"
            ],
            "words": [
                "If",
                "our",
                "teacher",
                "saw",
                "you",
                "smoking",
                "in",
                "class",
                "he",
                "will",
                "probably",
                "have",
                "a",
                "heart",
                "attack"
            ]
        }
    },
    {
        "That old man really is older than dirt": {
            "phrases": [
                "That old man really is older than dirt"
            ],
            "words": [
                "That",
                "old",
                "man",
                "really",
                "is",
                "older",
                "than",
                "dirt"
            ]
        }
    },
    {
        "Hey, give me a smoke": {
            "phrases": [
                "Hey, give me a smoke"
            ],
            "words": [
                "Hey",
                ",",
                "give",
                "me",
                "a",
                "smoke"
            ]
        }
    },
    {
        "Oh, so relaxing": {
            "phrases": [
                "Oh, so relaxing"
            ],
            "words": [
                "Oh",
                ",",
                "so",
                "relaxing"
            ]
        }
    },
    {
        "AHH!!!": {
            "phrases": [
                "AHH!!!"
            ],
            "words": [
                "AHH",
                "!!!"
            ]
        }
    },
    {
        "Big, bro,": {
            "phrases": [
                "Big, bro,"
            ],
            "words": [
                "Big",
                ",",
                "bro",
                ","
            ]
        }
    },
    {
        "I'm really really sorry": {
            "phrases": [
                "I am really really sorry"
            ],
            "words": [
                "I",
                "am",
                "really",
                "really",
                "sorry"
            ]
        }
    },
    {
        "Sorry, it's my fault": {
            "phrases": [
                "Sorry, it is my fault"
            ],
            "words": [
                "Sorry",
                ",",
                "it",
                "is",
                "my",
                "fault"
            ]
        }
    },
    {
        "I didn't do it on purpose, please spare me!": {
            "phrases": [
                "I did not do it on purpose, please spare me!"
            ],
            "words": [
                "I",
                "did",
                "not",
                "do",
                "it",
                "on",
                "purpose",
                ",",
                "please",
                "spare",
                "me",
                "!"
            ]
        }
    },
    {
        "You know,": {
            "phrases": [
                "You know,"
            ],
            "words": [
                "You",
                "know",
                ","
            ]
        }
    },
    {
        "I value cleanliness over everything!": {
            "phrases": [
                "I value cleanliness over everything!"
            ],
            "words": [
                "I",
                "value",
                "cleanliness",
                "over",
                "everything",
                "!"
            ]
        }
    },
    {
        "Hmph,": {
            "phrases": [
                "Hmph,"
            ],
            "words": [
                "Hmph",
                ","
            ]
        }
    },
    {
        "Lets go!": {
            "phrases": [
                "Let Us go!"
            ],
            "words": [
                "Let",
                "Us",
                "go",
                "!"
            ]
        }
    },
    {
        "I need to pee": {
            "phrases": [
                "I need to pee"
            ],
            "words": [
                "I",
                "need",
                "to",
                "pee"
            ]
        }
    },
    {
        "Huh?": {
            "phrases": [
                "Huh?"
            ],
            "words": [
                "Huh",
                "?"
            ]
        }
    },
    {
        "Is he alright?": {
            "phrases": [
                "Is he alright?"
            ],
            "words": [
                "Is",
                "he",
                "alright",
                "?"
            ]
        }
    },
    {
        "Relax,": {
            "phrases": [
                "Relax,"
            ],
            "words": [
                "Relax",
                ","
            ]
        }
    },
    {
        "His ability is to take beatings": {
            "phrases": [
                "His ability is to take beatings"
            ],
            "words": [
                "His",
                "ability",
                "is",
                "to",
                "take",
                "beatings"
            ]
        }
    },
    {
        "Big bro,": {
            "phrases": [
                "Big bro,"
            ],
            "words": [
                "Big",
                "bro",
                ","
            ]
        }
    },
    {
        "Big bro!": {
            "phrases": [
                "Big bro!"
            ],
            "words": [
                "Big",
                "bro",
                "!"
            ]
        }
    },
    {
        "Let me pee with you!": {
            "phrases": [
                "Let me pee with you!"
            ],
            "words": [
                "Let",
                "me",
                "pee",
                "with",
                "you",
                "!"
            ]
        }
    },
    {
        "Wow!": {
            "phrases": [
                "Wow!"
            ],
            "words": [
                "Wow",
                "!"
            ]
        }
    },
    {
        "As expected from big bro": {
            "phrases": [
                "As expected from big bro"
            ],
            "words": [
                "As",
                "expected",
                "from",
                "big",
                "bro"
            ]
        }
    },
    {
        "He even excels in peeing!": {
            "phrases": [
                "He even excels in peeing!"
            ],
            "words": [
                "He",
                "even",
                "excels",
                "in",
                "peeing",
                "!"
            ]
        }
    },
    {
        "Of course, of course, hehehe": {
            "phrases": [
                "Of course, of course, hehehe"
            ],
            "words": [
                "Of",
                "course",
                ",",
                "of",
                "course",
                ",",
                "hehehe"
            ]
        }
    },
    {
        "That's why I'm big bro": {
            "phrases": [
                "That is why I am big bro"
            ],
            "words": [
                "That",
                "is",
                "why",
                "I",
                "am",
                "big",
                "bro"
            ]
        }
    },
    {
        "Of course, of course, hehehe": {
            "phrases": [
                "Of course, of course, hehehe"
            ],
            "words": [
                "Of",
                "course",
                ",",
                "of",
                "course",
                ",",
                "hehehe"
            ]
        }
    },
    {
        "Not anyone can become big bro": {
            "phrases": [
                "Not anyone can become big bro"
            ],
            "words": [
                "Not",
                "anyone",
                "can",
                "become",
                "big",
                "bro"
            ]
        }
    },
    {
        "Got a lighter?": {
            "phrases": [
                "Got a lighter?"
            ],
            "words": [
                "Got",
                "a",
                "lighter",
                "?"
            ]
        }
    },
    {
        "AHH!!!": {
            "phrases": [
                "AHH!!!"
            ],
            "words": [
                "AHH",
                "!!!"
            ]
        }
    },
    {
        "It's a monster!": {
            "phrases": [
                "It is a monster!"
            ],
            "words": [
                "It",
                "is",
                "a",
                "monster",
                "!"
            ]
        }
    },
    {
        "Save me!": {
            "phrases": [
                "Save me!"
            ],
            "words": [
                "Save",
                "me",
                "!"
            ]
        }
    },
    {
        "Do you have a lighter or not?": {
            "phrases": [
                "Do you have a lighter or not?"
            ],
            "words": [
                "Do",
                "you",
                "have",
                "a",
                "lighter",
                "or",
                "not",
                "?"
            ]
        }
    },
    {
        "Are you human or mushroom?": {
            "phrases": [
                "Are you human or mushroom?"
            ],
            "words": [
                "Are",
                "you",
                "human",
                "or",
                "mushroom",
                "?"
            ]
        }
    },
    {
        "Of course I'm human": {
            "phrases": [
                "Of course I am human"
            ],
            "words": [
                "Of",
                "course",
                "I",
                "am",
                "human"
            ]
        }
    },
    {
        "Do humans dress like that?": {
            "phrases": [
                "Do humans dress like that?"
            ],
            "words": [
                "Do",
                "humans",
                "dress",
                "like",
                "that",
                "?"
            ]
        }
    },
    {
        "Oh,": {
            "phrases": [
                "Oh,"
            ],
            "words": [
                "Oh",
                ","
            ]
        }
    },
    {
        "This is how I express myself": {
            "phrases": [
                "This is how I express myself"
            ],
            "words": [
                "This",
                "is",
                "how",
                "I",
                "express",
                "myself"
            ]
        }
    },
    {
        "Last night I had this feeling": {
            "phrases": [
                "Last night I had this feeling"
            ],
            "words": [
                "Last",
                "night",
                "I",
                "had",
                "this",
                "feeling"
            ]
        }
    },
    {
        "A mushroom that was reborn": {
            "phrases": [
                "A mushroom that was reborn"
            ],
            "words": [
                "A",
                "mushroom",
                "that",
                "was",
                "reborn"
            ]
        }
    },
    {
        "Larger than before": {
            "phrases": [
                "Larger than before"
            ],
            "words": [
                "Larger",
                "than",
                "before"
            ]
        }
    },
    {
        "More yellow": {
            "phrases": [
                "More yellow"
            ],
            "words": [
                "More",
                "yellow"
            ]
        }
    },
    {
        "More beautiful": {
            "phrases": [
                "More beautiful"
            ],
            "words": [
                "More",
                "beautiful"
            ]
        }
    },
    {
        "And living once again!": {
            "phrases": [
                "And living once again!"
            ],
            "words": [
                "And",
                "living",
                "once",
                "again",
                "!"
            ]
        }
    },
    {
        "Fuck me,": {
            "phrases": [
                "Fuck me,"
            ],
            "words": [
                "Fuck",
                "me",
                ","
            ]
        }
    },
    {
        "So it was a cosplay": {
            "phrases": [
                "So it was a cosplay"
            ],
            "words": [
                "So",
                "it",
                "was",
                "a",
                "cosplay"
            ]
        }
    },
    {
        "That scared the shit out of big bro": {
            "phrases": [
                "That scared the shit out of big bro"
            ],
            "words": [
                "That",
                "scared",
                "the",
                "shit",
                "out",
                "of",
                "big",
                "bro"
            ]
        }
    },
    {
        "Huh?": {
            "phrases": [
                "Huh?"
            ],
            "words": [
                "Huh",
                "?"
            ]
        }
    },
    {
        "Fuck me!": {
            "phrases": [
                "Fuck me!"
            ],
            "words": [
                "Fuck",
                "me",
                "!"
            ]
        }
    },
    {
        "I peed all over my pants!": {
            "phrases": [
                "I peed all over my pants!"
            ],
            "words": [
                "I",
                "peed",
                "all",
                "over",
                "my",
                "pants",
                "!"
            ]
        }
    },
    {
        "Woah!": {
            "phrases": [
                "Woah!"
            ],
            "words": [
                "Woah",
                "!"
            ]
        }
    },
    {
        "So much pee!": {
            "phrases": [
                "So much pee!"
            ],
            "words": [
                "So",
                "much",
                "pee",
                "!"
            ]
        }
    },
    {
        "Someone's going to die!": {
            "phrases": [
                "Someone is going to die!"
            ],
            "words": [
                "Someone",
                "is",
                "going",
                "to",
                "die",
                "!"
            ]
        }
    },
    {
        "Run for your lives!": {
            "phrases": [
                "Run for your lives!"
            ],
            "words": [
                "Run",
                "for",
                "your",
                "lives",
                "!"
            ]
        }
    },
    {
        "There's trouble, big bro wet himself!": {
            "phrases": [
                "There is trouble, big bro wet himself!"
            ],
            "words": [
                "There",
                "is",
                "trouble",
                ",",
                "big",
                "bro",
                "wet",
                "himself",
                "!"
            ]
        }
    },
    {
        "Big bro has OCD, he really values cleanliness": {
            "phrases": [
                "Big bro has OCD, he really values cleanliness"
            ],
            "words": [
                "Big",
                "bro",
                "has",
                "OCD",
                ",",
                "he",
                "really",
                "values",
                "cleanliness"
            ]
        }
    },
    {
        "How do you want to die?": {
            "phrases": [
                "How do you want to die?"
            ],
            "words": [
                "How",
                "do",
                "you",
                "want",
                "to",
                "die",
                "?"
            ]
        }
    },
    {
        "So do you have a lighter or not?": {
            "phrases": [
                "So do you have a lighter or not?"
            ],
            "words": [
                "So",
                "do",
                "you",
                "have",
                "a",
                "lighter",
                "or",
                "not",
                "?"
            ]
        }
    },
    {
        "AHH!!!": {
            "phrases": [
                "AHH!!!"
            ],
            "words": [
                "AHH",
                "!!!"
            ]
        }
    },
    {
        "(What's happening?)": {
            "phrases": [
                "(What is happening?)"
            ],
            "words": [
                "(",
                "What",
                "is",
                "happening",
                "?",
                ")"
            ]
        }
    },
    {
        "Huh?": {
            "phrases": [
                "Huh?"
            ],
            "words": [
                "Huh",
                "?"
            ]
        }
    },
    {
        "Way too brutal!": {
            "phrases": [
                "Way too brutal!"
            ],
            "words": [
                "Way",
                "too",
                "brutal",
                "!"
            ]
        }
    },
    {
        "Hey bro": {
            "phrases": [
                "Hey bro"
            ],
            "words": [
                "Hey",
                "bro"
            ]
        }
    },
    {
        "Don't just resort to violence": {
            "phrases": [
                "Do not just resort to violence"
            ],
            "words": [
                "Do",
                "not",
                "just",
                "resort",
                "to",
                "violence"
            ]
        }
    },
    {
        "I'm well trained": {
            "phrases": [
                "I am well trained"
            ],
            "words": [
                "I",
                "am",
                "well",
                "trained"
            ]
        }
    },
    {
        "Dealing with you ordinary people": {
            "phrases": [
                "Dealing with you ordinary people"
            ],
            "words": [
                "Dealing",
                "with",
                "you",
                "ordinary",
                "people"
            ]
        }
    },
    {
        "It feels like I'm bullying you": {
            "phrases": [
                "It feels like I am bullying you"
            ],
            "words": [
                "It",
                "feels",
                "like",
                "I",
                "am",
                "bullying",
                "you"
            ]
        }
    },
    {
        "I'll have to show them": {
            "phrases": [
                "I will have to show them"
            ],
            "words": [
                "I",
                "will",
                "have",
                "to",
                "show",
                "them"
            ]
        }
    },
    {
        "That I'm not worth picking on": {
            "phrases": [
                "That I am not worth picking on"
            ],
            "words": [
                "That",
                "I",
                "am",
                "not",
                "worth",
                "picking",
                "on"
            ]
        }
    },
    {
        "Don, don, don, don't kill me!": {
            "phrases": [
                "Don, don, don, do not kill me!"
            ],
            "words": [
                "Don",
                ",",
                "don",
                ",",
                "don",
                ",",
                "do",
                "not",
                "kill",
                "me",
                "!"
            ]
        }
    },
    {
        "It's just a lighter": {
            "phrases": [
                "It is just a lighter"
            ],
            "words": [
                "It",
                "is",
                "just",
                "a",
                "lighter"
            ]
        }
    },
    {
        "You, you": {
            "phrases": [
                "You, you"
            ],
            "words": [
                "You",
                ",",
                "you"
            ]
        }
    },
    {
        "Just what type of person are you?": {
            "phrases": [
                "Just what type of person are you?"
            ],
            "words": [
                "Just",
                "what",
                "type",
                "of",
                "person",
                "are",
                "you",
                "?"
            ]
        }
    },
    {
        "Me?": {
            "phrases": [
                "Me?"
            ],
            "words": [
                "Me",
                "?"
            ]
        }
    },
    {
        "I'm a new transfer student": {
            "phrases": [
                "I am a new transfer student"
            ],
            "words": [
                "I",
                "am",
                "a",
                "new",
                "transfer",
                "student"
            ]
        }
    },
    {
        "Yeyan is my name": {
            "phrases": [
                "Yeyan is my name"
            ],
            "words": [
                "Yeyan",
                "is",
                "my",
                "name"
            ]
        }
    },
    {
        "We'll be going to the same school together": {
            "phrases": [
                "We will be going to the same school together"
            ],
            "words": [
                "We",
                "will",
                "be",
                "going",
                "to",
                "the",
                "same",
                "school",
                "together"
            ]
        }
    },
    {
        "Please look after me": {
            "phrases": [
                "Please look after me"
            ],
            "words": [
                "Please",
                "look",
                "after",
                "me"
            ]
        }
    },
    {
        "90 of people are troubled in some way": {
            "phrases": [
                "90 of people are troubled in some way"
            ],
            "words": [
                "90",
                "of",
                "people",
                "are",
                "troubled",
                "in",
                "some",
                "way"
            ]
        }
    },
    {
        "Living will result in facing these problems": {
            "phrases": [
                "Living will result in facing these problems"
            ],
            "words": [
                "Living",
                "will",
                "result",
                "in",
                "facing",
                "these",
                "problems"
            ]
        }
    },
    {
        "Sports betting is harmful": {
            "phrases": [
                "Sports betting is harmful"
            ],
            "words": [
                "Sports",
                "betting",
                "is",
                "harmful"
            ]
        }
    },
    {
        "Avoid the World Cup": {
            "phrases": [
                "Avoid the World Cup"
            ],
            "words": [
                "Avoid",
                "the",
                "World",
                "Cup"
            ]
        }
    },
    {
        "Any problem can be overcome": {
            "phrases": [
                "Any problem can be overcome"
            ],
            "words": [
                "Any",
                "problem",
                "can",
                "be",
                "overcome"
            ]
        }
    },
    {
        "The struggles in life will only improve your brilliance": {
            "phrases": [
                "The struggles in life will only improve your brilliance"
            ],
            "words": [
                "The",
                "struggles",
                "in",
                "life",
                "will",
                "only",
                "improve",
                "your",
                "brilliance"
            ]
        }
    },
    {
        "90 of people are troubled in some way": {
            "phrases": [
                "90 of people are troubled in some way"
            ],
            "words": [
                "90",
                "of",
                "people",
                "are",
                "troubled",
                "in",
                "some",
                "way"
            ]
        }
    },
    {
        "That freaking mushroom": {
            "phrases": [
                "That freaking mushroom"
            ],
            "words": [
                "That",
                "freaking",
                "mushroom"
            ]
        }
    },
    {
        "I,": {
            "phrases": [
                "I,"
            ],
            "words": [
                "I",
                ","
            ]
        }
    },
    {
        "I'll never let you get away with this!": {
            "phrases": [
                "I will never let you get away with this!"
            ],
            "words": [
                "I",
                "will",
                "never",
                "let",
                "you",
                "get",
                "away",
                "with",
                "this",
                "!"
            ]
        }
    },
    {
        "Acho!": {
            "phrases": [
                "Acho!"
            ],
            "words": [
                "Acho",
                "!"
            ]
        }
    },
    {
        "This is also the feeling I had yesterday": {
            "phrases": [
                "This is also the feeling I had yesterday"
            ],
            "words": [
                "This",
                "is",
                "also",
                "the",
                "feeling",
                "I",
                "had",
                "yesterday"
            ]
        }
    },
    {
        "A suicidal young girl": {
            "phrases": [
                "A suicidal young girl"
            ],
            "words": [
                "A",
                "suicidal",
                "young",
                "girl"
            ]
        }
    },
    {
        "It's artistic isn't it?": {
            "phrases": [
                "It is artistic is not it?"
            ],
            "words": [
                "It",
                "is",
                "artistic",
                "is",
                "not",
                "it",
                "?"
            ]
        }
    }
]